gem/__version__.py
global_equity_momentum-1.0.1.dist-info/METADATA
global_equity_momentum-1.0.1.dist-info/WHEEL
global_equity_momentum-1.0.1.dist-info/licenses/LICENSE
global_equity_momentum-1.0.1.dist-info/RECORD
