Metadata-Version: 2.4
Name: global-equity-momentum
Version: 1.0.1
Summary: Dual Momentum Investing Strategy Tool
Project-URL: Repository, https://github.com/karta9821/global-equity-momentum
Project-URL: Homepage, https://github.com/karta9821/global-equity-momentum
License: The MIT License (MIT)
License-File: LICENSE
Classifier: Framework :: Hatch
Classifier: License :: OSI Approved :: MIT License
Classifier: Programming Language :: Python
Classifier: Programming Language :: Python :: 3.13
Requires-Python: >=3.13
Requires-Dist: loguru>=0.7.3
Requires-Dist: matplotlib>=3.10.5
Requires-Dist: pandas>=2.3.1
Requires-Dist: seaborn>=0.13.2
Requires-Dist: yfinance>=0.2.65
